Workbook
Name spotify_data_clean: Data!$A$1:$O$8583

Sheet Data quality
A2: Column name | B2: track_id | C2: track_name | D2: track_number | E2: track_popularity | F2: explicit | G2: artist_name | H2: artist_popularity | I2: artist_followers | J2: artist_genres | K2: album_id | L2: album_name | M2: album_release_date | N2: album_total_tracks | O2: album_type | P2: track_duration_min
A3: % of blank | B3: =COUNTBLANK(Data!A2:A8583)/COUNTA(Data!A2:A8583) -> 0 | C3: =COUNTBLANK(Data!B2:B8583)/COUNTA(Data!B2:B8583) -> 0 | D3: =COUNTBLANK(Data!C2:C8583)/COUNTA(Data!C2:C8583) -> 0 | E3: =COUNTBLANK(Data!D2:D8583)/COUNTA(Data!D2:D8583) -> 0 | F3: =COUNTBLANK(Data!E2:E8583)/COUNTA(Data!E2:E8583) -> 0 | G3: =COUNTBLANK(Data!F2:F8583)/COUNTA(Data!F2:F8583) -> 0 | H3: =COUNTBLANK(Data!G2:G8583)/COUNTA(Data!G2:G8583) -> 0 | I3: =COUNTBLANK(Data!H2:H8583)/COUNTA(Data!H2:H8583) -> 0 | ... P3: =COUNTBLANK(Data!O2:O8583)/COUNTA(Data!O2:O8583) -> 0
A4: % of n/a | B4: =COUNTIF(Data!A2:A8583,"N/A")/COUNTA(Data!A2:A8583) -> 0 | C4: =COUNTIF(Data!B2:B8583,"N/A")/COUNTA(Data!B2:B8583) -> 0 | D4: =COUNTIF(Data!C2:C8583,"N/A")/COUNTA(Data!C2:C8583) -> 0 | E4: =COUNTIF(Data!D2:D8583,"N/A")/COUNTA(Data!D2:D8583) -> 0 | F4: =COUNTIF(Data!E2:E8583,"N/A")/COUNTA(Data!E2:E8583) -> 0 | G4: =COUNTIF(Data!F2:F8583,"N/A")/COUNTA(Data!F2:F8583) -> 0.00034956887 | H4: =COUNTIF(Data!G2:G8583,"N/A")/COUNTA(Data!G2:G8583) -> 0 | I4: =COUNTIF(Data!H2:H8583,"N/A")/COUNTA(Data!H2:H8583) -> 0 | ... P4: =COUNTIF(Data!O2:O8583,"N/A")/COUNTA(Data!O2:O8583) -> 0

Sheet Data
A1: track_id | B1: track_name | C1: track_number | D1: track_popularity | E1: explicit | F1: artist_name | G1: artist_popularity | H1: artist_followers | I1: artist_genres | J1: album_id | K1: album_name | L1: album_release_date | M1: album_total_tracks | N1: album_type | O1: track_duration_min
A2: 3EJS5LyekDim1Tf5rBFmZl | B2: Trippy Mane (ft. Project Pat) | C2: 4 | D2: 0 | E2: TRUE | F2: Diplo | G2: 77 | H2: 2812821 | I2: moombahton | J2: 5QRFnGnBeMGePBKF2xTz5z | K2: d00mscrvll, Vol. 1 | L2: 45961 | M2: 9 | N2: album | O2: 1.55
A3: 1oQW6G2ZiwMuHqlPpP27DB | B3: OMG! | C3: 1 | D3: 0 | E3: TRUE | F3: Yelawolf | G3: 64 | H3: 2363438 | I3: country hip hop, southern hip hop | J3: 4SUmmwnv0xTjRcLdjczGg2 | K3: OMG! | L3: 45961 | M3: 1 | N3: single | O3: 3.07
A4: 7mdkjzoIYlf1rx9EtBpGmU | B4: Hard 2 Find | C4: 1 | D4: 4 | E4: TRUE | F4: Riff Raff | G4: 48 | H4: 193302 | I4: N/A | J4: 3E3zEAL8gUYWaLYB9L7gbp | K4: Hard 2 Find | L4: 45961 | M4: 1 | N4: single | O4: 2.55
A5: 67rW0Zl7oB3qEpD5YWWE5w | B5: Still Get Like That (ft. Project Pat & Starrah) | C5: 8 | D5: 30 | E5: TRUE | F5: Diplo | G5: 77 | H5: 2813710 | I5: moombahton | J5: 5QRFnGnBeMGePBKF2xTz5z | K5: d00mscrvll, Vol. 1 | L5: 45961 | M5: 9 | N5: album | O5: 1.69
A6: 15xptTfRBrjsppW0INUZjf | B6: ride me like a harley | C6: 2 | D6: 0 | E6: TRUE | F6: Rumelis | G6: 48 | H6: 8682 | I6: dark r&b | J6: 06FDIpSHYmZAZoyuYtc7kd | K6: come closer / ride me like a harley | L6: 45960 | M6: 2 | N6: single | O6: 2.39
A7: 4ccpCcZYseq8VrPMK1EDs0 | B7: BLEED | C7: 1 | D7: 2 | E7: FALSE | F7: Minzie | G7: 46 | H7: 7218 | I7: dark r&b | J7: 2NQv9p3ZQW0Ed1LB9enix8 | K7: BLEED | L7: 45960 | M7: 3 | N7: single | O7: 2.76
A8: 3QoQ3HqXTAjgEl9LbNMbYp | B8: Te Procuro na Cidade | C8: 1 | D8: 20 | E8: FALSE | F8: AZERDK | G8: 30 | H8: 1657 | I8: N/A | J8: 1PpuOsLjPWshDLxkr0oHeU | K8: Te Procuro na Cidade | L8: 45960 | M8: 1 | N8: single | O8: 4.12
A9: 1YEZbdT417SfolPQzaoHs2 | B9: come closer | C9: 1 | D9: 27 | E9: FALSE | F9: Rumelis | G9: 49 | H9: 8802 | I9: dark r&b | J9: 06FDIpSHYmZAZoyuYtc7kd | K9: come closer / ride me like a harley | L9: 45960 | M9: 2 | N9: single | O9: 2.53
A10: 4pZ949nFW5SurwzE0TSe7I | B10: Cupido Vagabundo | C10: 1 | D10: 16 | E10: FALSE | F10: Toni dos Anjos | G10: 6 | H10: 475 | I10: N/A | J10: 60DLQZkzpvDvVfvEC6VOJM | K10: Cupido Vagabundo | L10: 45960 | M10: 2 | N10: single | O10: 2.92
A11: 0L0LgwFZ7UtBnRNQvSBty6 | B11: LET‚ÄôS GO! | C11: 1 | D11: 33 | E11: TRUE | F11: PsychoYP | G11: 48 | H11: 154802 | I11: nigerian drill, alt√©, afro adura, afrobeats, afrobeat, afroswing | J11: 3ARxksm8CspGeAaZZB1v2w | K11: LET‚ÄôS GO! | L11: 45958 | M11: 1 | N11: single | O11: 2.4
A12: 5mfAZwEr4jAVDnSY0HHuyH | B12: Stray | C12: 1 | D12: 30 | E12: FALSE | F12: What Matters The Most | G12: 25 | H12: 814 | I12: N/A | J12: 0DHsJaaMzbygWosCjYk37t | K12: Stray | L12: 45955 | M12: 4 | N12: single | O12: 2.49
A13: 4V1Sh9Y2z6e8HpzNOet5rC | B13: PAPARAZZI ARRIVE - English Ver. | C13: 1 | D13: 48 | E13: FALSE | F13: A2O | G13: 46 | H13: 13826 | I13: c-pop | J13: 54XcHEnJ2BKMOzkeRrRubu | K13: PAPARAZZI ARRIVE | L13: 45954 | M13: 14 | N13: album | O13: 2.89
... A37: 1nNgDKWWX9MU9cp5FrHXRN | B37: Love Crazy - Stash Konig Remix | C37: 1 | D37: 31 | E37: FALSE | F37: MisterNez | G37: 18 | H37: 200 | I37: N/A | J37: 2kepsE9qO2QRTLCsF1byjn | K37: Love Crazy (Stash Konig Remix) | L37: 45950 | M37: 1 | N37: single | O37: 3.26
A38: 4ljqKsDyZzicNpBIMvDaZ5 | B38: One More Time | C38: 5 | D38: 6 | E38: FALSE | F38: Fraser Stott | G38: 13 | H38: 119 | I38: N/A | J38: 179fPnGB9pMjUUH2pT02o0 | K38: 19 | L38: 45949 | M38: 9 | N38: album | O38: 3.94
A39: 5hw7dvgBRLvlCiALWwujYz | B39: Nectar - B-Rain Remix | C39: 2 | D39: 29 | E39: FALSE | F39: Senhit | G39: 27 | H39: 54636 | I39: N/A | J39: 4Z53gLriAjTmR7DQr1LRY4 | K39: Nectar (The Remixes) | L39: 45947 | M39: 3 | N39: single | O39: 2.95
A40: 6OTDBDVaK18xlne9rlGQok | B40: No Glory | C40: 1 | D40: 52 | E40: FALSE | F40: Besomorph | G40: 58 | H40: 146944 | I40: slap house | J40: 1jO43qFvbxg7hdp2LgMmyw | K40: No Glory | L40: 45947 | M40: 1 | N40: single | O40: 2.37
A41: 1NXbNEAcPvY5G1xvfN57aA | B41: Dracula | C41: 3 | D41: 80 | E41: TRUE | F41: Tame Impala | G41: 84 | H41: 9509731 | I41: neo-psychedelic, indie | J41: 5WulAOx9ilWy1h8UGZ1gkI | K41: Deadbeat | L41: 45947 | M41: 12 | N41: album | O41: 3.42
A42: 6gRNWnK8b8BVfzrF65HGcf | B42: PSYCHWARD (with WesGhost ft. Project Pat) | C42: 1 | D42: 51 | E42: TRUE | F42: Diplo | G42: 77 | H42: 2812337 | I42: moombahton | J42: 5oq9z5XNldcl7wTiEamVvo | K42: PSYCHWARD | L42: 45947 | M42: 4 | N42: single | O42: 2.88
A43: 1e73KA7YWgIS9cLszZJRTu | B43: Where Have You Been | C43: 1 | D43: 38 | E43: FALSE | F43: Ken | G43: 50 | H43: 7219 | I43: hypertechno | J43: 5OPlNhEIlxUifin4l0gPL6 | K43: Where Have You Been | L43: 45947 | M43: 1 | N43: single | O43: 2.08
A44: 44NbFZ0gEZ4U0LMMsHWyb3 | B44: Great Tomorrow | C44: 1 | D44: 3 | E44: FALSE | F44: Kxng Le√≥ | G44: 1 | H44: 177 | I44: N/A | J44: 0jFDIZgcya0j2cfR17izT9 | K44: Great Tomorrow | L44: 45947 | M44: 1 | N44: single | O44: 2.21
A45: 05RK4klU7S2Jm50ONIjyM4 | B45: Hearts Grow Cold (Saint No√´l) [feat. Olivia Cadenza] | C45: 1 | D45: 50 | E45: FALSE | F45: Kayote | G45: 49 | H45: 19306 | I45: N/A | J45: 0Kil1i9WrmbacxToZg8qk9 | K45: Hearts Grow Cold (Saint No√™l) [feat. Olivia Cadenza] | L45: 45947 | M45: 1 | N45: single | O45: 2.65
A46: 0Oriikd4ETp5qmzek6ZUD5 | B46: Talk To You (ft. Elton John) | C46: 1 | D46: 72 | E46: TRUE | F46: Sam Fender | G46: 73 | H46: 1204977 | I46: N/A | J46: 5tmaU5xBUYQYr2VkWhokIb | K46: Talk To You (ft. Elton John) | L46: 45947 | M46: 1 | N46: single | O46: 5.28
A47: 5jw5yNpSTxdBAr1AV3N96s | B47: The Way I Am Now | C47: 1 | D47: 25 | E47: FALSE | F47: Lila Holler | G47: 17 | H47: 1068 | I47: N/A | J47: 7xpJHorbY32dNwaRlBgXC5 | K47: The Way I Am Now | L47: 45947 | M47: 1 | N47: single | O47: 3.77
A48: 0lRnxwJeUOxwEvWMw4uQKj | B48: Think About Us | C48: 1 | D48: 68 | E48: FALSE | F48: Sonny Fodera | G48: 66 | H48: 306842 | I48: house | J48: 1jmVSpWhzD8vciWg2Qtd5V | K48: Think About Us | L48: 45947 | M48: 1 | N48: single | O48: 2.96
A49: 6q43CVVE0VXEWlDjPdgH0c | B49: Trophy Wife | C49: 1 | D49: 32 | E49: TRUE | F49: Annalise Azadian | G49: 31 | H49: 5701 | I49: N/A | J49: 5XWqunjy0GiCQIOLtEyuyr | K49: Trophy Wife | L49: 45947 | M49: 1 | N49: single | O49: 2.86
A50: 0vXBmU9Zus9ZtbR4kvZAjH | B50: baby can you sin for me | C50: 1 | D50: 52 | E50: FALSE | F50: Ex Habit | G50: 59 | H50: 130408 | I50: dark r&b | J50: 5eudqcLVRKtOtQdlHQ2yrm | K50: baby can you sin for me | L50: 45946 | M50: 1 | N50: single | O50: 2.69
... A407: 5H1sKFMzDeMtXwND3V6hRY | B407: JUMP | C407: 1 | D407: 90 | E407: FALSE | F407: BLACKPINK | G407: 81 | H407: 56152334 | I407: k-pop | J407: 3hzoZlx2KwtvJEUl9piPWr | K407: JUMP | L407: 45849 | M407: 1 | N407: single | O407: 2.74
A408: 7gCautqfD7CCdrN33GrRd8 | B408: 405 | C408: 17 | D408: 63 | E408: FALSE | F408: Justin Bieber | G408: 91 | H408: 85008100 | I408: pop, contemporary r&b | J408: 5vD5M5VW62LL78Ko8x0CVZ | K408: SWAG | L408: 45849 | M408: 21 | N408: album | O408: 3.54
A409: 72PVbRKkUimweUPV0nKAPs | B409: ALL I CAN TAKE | C409: 1 | D409: 71 | E409: FALSE | F409: Justin Bieber | G409: 91 | H409: 85050158 | I409: pop, contemporary r&b | J409: 5vD5M5VW62LL78Ko8x0CVZ | K409: SWAG | L409: 45849 | M409: 21 | N409: album | O409: 4.12
A410: 0lUXjVdwD90F7coLj0aabz | B410: Alright | C410: 1 | D410: 45 | E410: FALSE | F410: Scoobert Doobert | G410: 36 | H410: 5521 | I410: N/A | J410: 1wvfvKidzPjbiGFBEb0n5T | K410: Alright | L410: 45849 | M410: 1 | N410: single | O410: 3.36
A411: 5cfsQZEFf1IpQr8F9vI9le | B411: BUTTERFLIES | C411: 6 | D411: 67 | E411: FALSE | F411: Justin Bieber | G411: 91 | H411: 85008100 | I411: pop, contemporary r&b | J411: 5vD5M5VW62LL78Ko8x0CVZ | K411: SWAG | L411: 45849 | M411: 21 | N411: album | O411: 3.22
A412: 1MVT5RV5LTO4FQ4bUKjvRr | B412: no one ever warns you | C412: 1 | D412: 32 | E412: FALSE | F412: Olivia Soli | G412: 15 | H412: 2381 | I412: N/A | J412: 6IMrYT25DPqimzpTOjtbwm | K412: no one ever warns you | L412: 45849 | M412: 1 | N412: single | O412: 3.25
A413: 5WqA7iqtEMmnN9nkdTSW2p | B413: Out Of The Dark | C413: 1 | D413: 52 | E413: FALSE | F413: LMNT 115 | G413: 35 | H413: 5813 | I413: N/A | J413: 1iTQQDXtrER9NQZMPGqKfZ | K413: Out Of The Dark | L413: 45849 | M413: 1 | N413: single | O413: 2.53
A414: 3WQ5w7ruC3c861lHXF9Gs2 | B414: SWAG | C414: 18 | D414: 65 | E414: TRUE | F414: Justin Bieber | G414: 91 | H414: 85008100 | I414: pop, contemporary r&b | J414: 5vD5M5VW62LL78Ko8x0CVZ | K414: SWAG | L414: 45849 | M414: 21 | N414: album | O414: 2.5
A415: 6AX3i1TluzbvpJpKrY7NoD | B415: SWEET SPOT | C415: 15 | D415: 66 | E415: TRUE | F415: Justin Bieber | G415: 91 | H415: 85022258 | I415: pop, contemporary r&b | J415: 5vD5M5VW62LL78Ko8x0CVZ | K415: SWAG | L415: 45849 | M415: 21 | N415: album | O415: 3.08
A416: 7tZlvvEpX3FEFoYsOI55FB | B416: THERAPY SESSION | C416: 14 | D416: 58 | E416: TRUE | F416: Justin Bieber | G416: 91 | H416: 85022258 | I416: pop, contemporary r&b | J416: 5vD5M5VW62LL78Ko8x0CVZ | K416: SWAG | L416: 45849 | M416: 21 | N416: album | O416: 1.31
A417: 1j8TmNa6vaFAEAws43kP0Q | B417: THINGS YOU DO | C417: 5 | D417: 70 | E417: FALSE | F417: Justin Bieber | G417: 91 | H417: 85022258 | I417: pop, contemporary r&b | J417: 5vD5M5VW62LL78Ko8x0CVZ | K417: SWAG | L417: 45849 | M417: 21 | N417: album | O417: 1.8
A418: 422PeUrBywndaCCxL6bDBj | B418: TOO LONG | C418: 20 | D418: 65 | E418: TRUE | F418: Justin Bieber | G418: 91 | H418: 85008100 | I418: pop, contemporary r&b | J418: 5vD5M5VW62LL78Ko8x0CVZ | K418: SWAG | L418: 45849 | M418: 21 | N418: album | O418: 3.07
A419: 6Ql76QUTIXajTh9cVjrAZl | B419: Vodka Cranberry | C419: 1 | D419: 72 | E419: FALSE | F419: Conan Gray | G419: 79 | H419: 12428221 | I419: N/A | J419: 0Z5FaBjNQ1sZ2Udunf17Jt | K419: Vodka Cranberry | L419: 45849 | M419: 2 | N419: single | O419: 4.09
A420: 0LutvoC2HqCfnaRSjrhtzo | B420: WALKING AWAY | C420: 10 | D420: 74 | E420: TRUE | F420: Justin Bieber | G420: 91 | H420: 85008100 | I420: pop, contemporary r&b | J420: 5vD5M5VW62LL78Ko8x0CVZ | K420: SWAG | L420: 45849 | M420: 21 | N420: album | O420: 4.06
... A651: 2exZDvIQ0f6jxiazDRjK1u | B651: Zombie | C651: 8 | D651: 48 | E651: FALSE | F651: Last Call | G651: 49 | H651: 2083 | I651: N/A | J651: 3cdL02bWDiOWlAsoJ84ygV | K651: On Tap | L651: 45721 | M651: 8 | N651: album | O651: 2.51
A652: 6uTNaZG0i5VRdckzFr1M9u | B652: 505 | C652: 7 | D652: 55 | E652: FALSE | F652: Last Call | G652: 49 | H652: 2100 | I652: N/A | J652: 3cdL02bWDiOWlAsoJ84ygV | K652: On Tap | L652: 45721 | M652: 8 | N652: album | O652: 2.58
A653: 72ZMz4NApk0xZMdsBPqe8v | B653: Amazed | C653: 6 | D653: 52 | E653: FALSE | F653: JD & The Straight Chasers | G653: 49 | H653: 1874 | I653: N/A | J653: 0DeP851WJ3Og8I49JYw6YZ | K653: Southern Comfort Classics | L653: 45721 | M653: 7 | N653: single | O653: 2.87
A654: 1musbempyJAw5gfSKZHXP9 | B654: Anxiety | C654: 1 | D654: 79 | E654: TRUE | F654: Doechii | G654: 76 | H654: 3227707 | I654: N/A | J654: 706mYHElAsR2MfcehZt2PA | K654: Anxiety | L654: 45721 | M654: 2 | N654: single | O654: 4.15
A655: 4JVgIFgTrlQ2XMWasExsLj | B655: Creep | C655: 2 | D655: 59 | E655: FALSE | F655: Last Call | G655: 49 | H655: 2083 | I655: N/A | J655: 3cdL02bWDiOWlAsoJ84ygV | K655: On Tap | L655: 45721 | M655: 8 | N655: album | O655: 2.52
A656: 1R3Y3bGE77KfOKLT4bN4mi | B656: Everlong | C656: 1 | D656: 53 | E656: FALSE | F656: Last Call | G656: 49 | H656: 2083 | I656: N/A | J656: 3cdL02bWDiOWlAsoJ84ygV | K656: On Tap | L656: 45721 | M656: 8 | N656: album | O656: 2.49
A657: 1ZA9k26vrQG6MfRSsbifk6 | B657: Fishin' In The Dark | C657: 2 | D657: 53 | E657: FALSE | F657: JD & The Straight Chasers | G657: 49 | H657: 1866 | I657: N/A | J657: 0DeP851WJ3Og8I49JYw6YZ | K657: Southern Comfort Classics | L657: 45721 | M657: 7 | N657: single | O657: 2.59
A658: 05TeoYmF2bJ5IyxskDro2e | B658: Sex On Fire | C658: 3 | D658: 57 | E658: FALSE | F658: October Surprise | G658: 48 | H658: 1921 | I658: N/A | J658: 6jJEhSUKlIu07ZdpRTrmEC | K658: Legends, Revisted | L658: 45721 | M658: 8 | N658: single | O658: 2.33
A659: 5wABKK13OJbFFFvJZyVf5V | B659: She's Country | C659: 1 | D659: 54 | E659: FALSE | F659: JD & The Straight Chasers | G659: 49 | H659: 1874 | I659: N/A | J659: 0DeP851WJ3Og8I49JYw6YZ | K659: Southern Comfort Classics | L659: 45721 | M659: 7 | N659: single | O659: 2.25
A660: 52cMgUC7UqXo022H06yUKR | B660: Something Like That | C660: 4 | D660: 50 | E660: FALSE | F660: JD & The Straight Chasers | G660: 49 | H660: 1855 | I660: N/A | J660: 0DeP851WJ3Og8I49JYw6YZ | K660: Southern Comfort Classics | L660: 45721 | M660: 7 | N660: single | O660: 2.97
A661: 0qZGM10IvZc3W0oPYaoehG | B661: Sweet Disposition | C661: 8 | D661: 52 | E661: FALSE | F661: October Surprise | G661: 48 | H661: 1950 | I661: N/A | J661: 6jJEhSUKlIu07ZdpRTrmEC | K661: Legends, Revisted | L661: 45721 | M661: 8 | N661: single | O661: 2.13
A662: 531apW6WGFUIKgTA1FhMPO | B662: Tennessee Whiskey | C662: 5 | D662: 54 | E662: FALSE | F662: JD & The Straight Chasers | G662: 49 | H662: 1874 | I662: N/A | J662: 0DeP851WJ3Og8I49JYw6YZ | K662: Southern Comfort Classics | L662: 45721 | M662: 7 | N662: single | O662: 4.73
A663: 1Sp1w7Pcc5dbODq4CCvUTb | B663: What Hurts The Most | C663: 7 | D663: 51 | E663: FALSE | F663: JD & The Straight Chasers | G663: 49 | H663: 1874 | I663: N/A | J663: 0DeP851WJ3Og8I49JYw6YZ | K663: Southern Comfort Classics | L663: 45721 | M663: 7 | N663: single | O663: 2.46
A664: 62Kl67cbs2k2fG0INkjYTd | B664: Life Is A Highway | C664: 3 | D664: 55 | E664: FALSE | F664: JD & The Straight Chasers | G664: 49 | H664: 1866 | I664: N/A | J664: 0DeP851WJ3Og8I49JYw6YZ | K664: Southern Comfort Classics | L664: 45721 | M664: 7 | N664: single | O664: 4.51
... A1099: 3Y1EvIgEVw51XtgNEgpz5c | B1099: Von dutch | C1099: 6 | D1099: 79 | E1099: TRUE | F1099: Charli xcx | G1099: 82 | H1099: 6318755 | I1099: hyperpop, art pop | J1099: 2lIZef4lzdvZkiiCzvPKj7 | K1099: BRAT | L1099: 45450 | M1099: 15 | N1099: album | O1099: 2.73
A1100: 4w2GLmK2wnioVnb5CPQeex | B1100: 360 | C1100: 1 | D1100: 76 | E1100: TRUE | F1100: Charli xcx | G1100: 82 | H1100: 6315216 | I1100: hyperpop, art pop | J1100: 2lIZef4lzdvZkiiCzvPKj7 | K1100: BRAT | L1100: 45450 | M1100: 15 | N1100: album | O1100: 2.23
A1101: 5h68SoVFGleijCtjEja3xG | B1101: 365 | C1101: 15 | D1101: 75 | E1101: TRUE | F1101: Charli xcx | G1101: 82 | H1101: 6318755 | I1101: hyperpop, art pop | J1101: 2lIZef4lzdvZkiiCzvPKj7 | K1101: BRAT | L1101: 45450 | M1101: 15 | N1101: album | O1101: 3.39
A1102: 1Dsee91MSgdtDmO4UNXiJo | B1102: 8 Years Old | C1102: 1 | D1102: 30 | E1102: FALSE | F1102: RIELL | G1102: 52 | H1102: 78478 | I1102: N/A | J1102: 5DeCSldptKixSNZGnM25jB | K1102: 8 Years Old | L1102: 45450 | M1102: 1 | N1102: single | O1102: 3.13
A1103: 19RybK6XDbAVpcdxSbZL1o | B1103: Apple | C1103: 11 | D1103: 76 | E1103: FALSE | F1103: Charli xcx | G1103: 82 | H1103: 6322030 | I1103: hyperpop, art pop | J1103: 2lIZef4lzdvZkiiCzvPKj7 | K1103: BRAT | L1103: 45450 | M1103: 15 | N1103: album | O1103: 2.52
A1104: 4wTvw1dBiPXNiHTh0zzpcI | B1104: B2b | C1104: 12 | D1104: 75 | E1104: FALSE | F1104: Charli xcx | G1104: 82 | H1104: 6318755 | I1104: hyperpop, art pop | J1104: 2lIZef4lzdvZkiiCzvPKj7 | K1104: BRAT | L1104: 45450 | M1104: 15 | N1104: album | O1104: 2.97
A1105: 5xR8ngEQmlQ1U2xSE0KzTo | B1105: BMXXing | C1105: 1 | D1105: 50 | E1105: TRUE | F1105: mgk | G1105: 78 | H1105: 5642365 | I1105: N/A | J1105: 5cH3Lzm6kYM7sxkpDprzkd | K1105: BMXXing | L1105: 45450 | M1105: 1 | N1105: single | O1105: 2.59
A1106: 50GxvQA2KEWNt31EdwIlzY | B1106: Rewind | C1106: 8 | D1106: 63 | E1106: FALSE | F1106: Charli xcx | G1106: 82 | H1106: 6318755 | I1106: hyperpop, art pop | J1106: 2lIZef4lzdvZkiiCzvPKj7 | K1106: BRAT | L1106: 45450 | M1106: 15 | N1106: album | O1106: 2.8
A1107: 0AkiAfilrTUXV49dleC5SB | B1107: So I | C1107: 9 | D1107: 62 | E1107: FALSE | F1107: Charli xcx | G1107: 82 | H1107: 6322030 | I1107: hyperpop, art pop | J1107: 2lIZef4lzdvZkiiCzvPKj7 | K1107: BRAT | L1107: 45450 | M1107: 15 | N1107: album | O1107: 3.52
A1108: 0PFZCt7UNmpas24HejQGu8 | B1108: I might say something stupid | C1108: 4 | D1108: 62 | E1108: FALSE | F1108: Charli xcx | G1108: 82 | H1108: 6318755 | I1108: hyperpop, art pop | J1108: 2lIZef4lzdvZkiiCzvPKj7 | K1108: BRAT | L1108: 45450 | M1108: 15 | N1108: album | O1108: 1.82
A1109: 3OaFGqHUyxGVkOcSILw8Kx | B1109: I think about it all the time | C1109: 14 | D1109: 59 | E1109: FALSE | F1109: Charli xcx | G1109: 82 | H1109: 6318755 | I1109: hyperpop, art pop | J1109: 2lIZef4lzdvZkiiCzvPKj7 | K1109: BRAT | L1109: 45450 | M1109: 15 | N1109: album | O1109: 2.26
A1110: 1vLqigPHwiFnXsfrLMehV1 | B1110: Espresso | C1110: 2 | D1110: 67 | E1110: FALSE | F1110: Sabrina Carpenter | G1110: 91 | H1110: 26516295 | I1110: pop | J1110: 2kFFrTliyBq4AnjDkPGVeD | K1110: Please Please Please | L1110: 45449 | M1110: 2 | N1110: single | O1110: 2.92
A1111: 5N3hjp1WNayUPZrA8kJmJP | B1111: Please Please Please | C1111: 1 | D1111: 79 | E1111: TRUE | F1111: Sabrina Carpenter | G1111: 91 | H1111: 26516295 | I1111: pop | J1111: 5bBaoign62r1i7OV8w7mi9 | K1111: Please Please Please | L1111: 45449 | M1111: 2 | N1111: single | O1111: 3.1
A1112: 5W26N7nM3mCmlxVCOCFwZZ | B1112: Divine - Acoustic Version | C1112: 1 | D1112: 0 | E1112: FALSE | F1112: Curos | G1112: 35 | H1112: 63897 | I1112: N/A | J1112: 6jU0AvEfVwlYIQAlBCc10Z | K1112: Divine (Acoustic Version) | L1112: 45448 | M1112: 1 | N1112: single | O1112: 3.2
A1113: 4I10wS3gXiR3UecwfDXDs9 | B1113: It Follows | C1113: 1 | D1113: 7 | E1113: FALSE | F1113: Cokasian | G1113: 27 | H1113: 4909 | I1113: darkwave, post-punk, cold wave | J1113: 0FIZfuyeIJoewIH1dPmzTU | K1113: It Follows | L1113: 45447 | M1113: 1 | N1113: single | O1113: 2.83
... A1355: 612RuAQh2xuXVqhdX3Jrfd | B1355: You Make My Heart Go | C1355: 1 | D1355: 53 | E1355: FALSE | F1355: Sad Puppy | G1355: 48 | H1355: 45292 | I1355: hypertechno | J1355: 2nb2U1WnJxggsC6pK1xgIr | K1355: You Make My Heart Go | L1355: 45343 | M1355: 1 | N1355: single | O1355: 2.1
A1356: 1ObrUCFugAMJoXcvpggbOd | B1356: Tell m√´ | C1356: 10 | D1356: 62 | E1356: TRUE | F1356: Yeat | G1356: 79 | H1356: 5976603 | I1356: rage rap | J1356: 1jXYc5gip5tqCTDOotfY5L | K1356: 2093 | L1356: 45338 | M1356: 22 | N1356: album | O1356: 4.06
A1357: 727x6SZXGF0LfU2vi3rjaH | B1357: Darlin' | C1357: 2 | D1357: 69 | E1357: FALSE | F1357: Chase Matthew | G1357: 64 | H1357: 468383 | I1357: country, country hip hop | J1357: 1XXkk3jAPfmW5jyRbRON7x | K1357: We All Grow Up | L1357: 45338 | M1357: 6 | N1357: single | O1357: 2.75
A1358: 6oGaiEmRukrU7cafXnnxph | B1358: linger x duvet | C1358: 1 | D1358: 0 | E1358: FALSE | F1358: SUKI | G1358: 29 | H1358: 3595 | I1358: N/A | J1358: 3bz3cs3AYDgy82ZwAFwj3d | K1358: linger x duvet | L1358: 45338 | M1358: 1 | N1358: single | O1358: 1.88
A1359: 2pZJqhsUxcS27EIw6osRBS | B1359: Now | C1359: 1 | D1359: 35 | E1359: FALSE | F1359: Niklas Dee | G1359: 64 | H1359: 84858 | I1359: hypertechno, slap house | J1359: 4bZgBjgSVUFi93sGfxRxkK | K1359: Now | L1359: 45338 | M1359: 1 | N1359: single | O1359: 2.91
A1360: 2EgFJVXw76TqnoSjwk7htO | B1360: Prada | C1360: 1 | D1360: 40 | E1360: FALSE | F1360: midnight Berlin | G1360: 42 | H1360: 4170 | I1360: hypertechno | J1360: 08LECZ7dTSaUtAgBYixrDS | K1360: Prada | L1360: 45338 | M1360: 2 | N1360: single | O1360: 2.12
A1361: 0YThXX1dqUpYBLyJNAsF9N | B1361: If We Being R√´al | C1361: 21 | D1361: 75 | E1361: TRUE | F1361: Yeat | G1361: 79 | H1361: 5978358 | I1361: rage rap | J1361: 1jXYc5gip5tqCTDOotfY5L | K1361: 2093 | L1361: 45338 | M1361: 22 | N1361: album | O1361: 2.87
A1362: 60ZYVMNQhHqlxnTAWKpuJa | B1362: Angel Of Darkness | C1362: 1 | D1362: 33 | E1362: FALSE | F1362: Ericovich | G1362: 41 | H1362: 11030 | I1362: nightcore | J1362: 7HBqMFmuwLTlnlGIAxSSZE | K1362: Angel Of Darkness | L1362: 45338 | M1362: 1 | N1362: single | O1362: 2.18
A1363: 2uqYupMHANxnwgeiXTZXzd | B1363: Austin (Boots Stop Workin') | C1363: 4 | D1363: 82 | E1363: TRUE | F1363: Dasha | G1363: 67 | H1363: 416933 | I1363: N/A | J1363: 40HsqPqeSR9Xe3IyAJWr6e | K1363: What Happens Now? | L1363: 45338 | M1363: 8 | N1363: album | O1363: 2.86
A1364: 5uQ7de4EWjb3rkcFxyEOpu | B1364: Belong Together | C1364: 1 | D1364: 75 | E1364: FALSE | F1364: Mark Ambor | G1364: 66 | H1364: 685131 | I1364: N/A | J1364: 3PlCMwyq6nuQYtoYproV1o | K1364: Belong Together | L1364: 45338 | M1364: 1 | N1364: single | O1364: 2.47
A1365: 6Qb7YsAqH4wWFUMbGsCpap | B1365: Training Season | C1365: 1 | D1365: 74 | E1365: FALSE | F1365: Dua Lipa | G1365: 85 | H1365: 46886554 | I1365: pop | J1365: 3sqC2sXZc0b9r7WM9z3784 | K1365: Training Season | L1365: 45337 | M1365: 4 | N1365: single | O1365: 3.49
A1366: 57wp7VFnV8X0pSVnYArGeJ | B1366: Whatever She Wants | C1366: 1 | D1366: 76 | E1366: TRUE | F1366: Bryson Tiller | G1366: 80 | H1366: 10566213 | I1366: trap soul, r&b | J1366: 60s0PMYFJhe34io9HuyUXf | K1366: Whatever She Wants | L1366: 45335 | M1366: 1 | N1366: single | O1366: 2.68
A1367: 0Z7nGFVCLfixWctgePsRk9 | B1367: TEXAS HOLD 'EM | C1367: 1 | D1367: 73 | E1367: TRUE | F1367: Beyonc√© | G1367: 84 | H1367: 41172203 | I1367: N/A | J1367: 6cBlaud5JVmPjkjxnwIMLx | K1367: TEXAS HOLD 'EM | L1367: 45333 | M1367: 1 | N1367: single | O1367: 3.89
A1368: 7AYmToZ5y67fBjq4RLFbuq | B1368: TEXAS HOLD 'EM | C1368: 1 | D1368: 58 | E1368: TRUE | F1368: Beyonc√© | G1368: 84 | H1368: 41172203 | I1368: N/A | J1368: 2NXwHjhgaAdkDy6GPSxMAd | K1368: TEXAS HOLD 'EM | L1368: 45332 | M1368: 3 | N1368: single | O1368: 3.89
A1369: 17UoqnSRKmsWbhInoFGq4F | B1369: Acquainted | C1369: 17 | D1369: 39 | E1369: TRUE | F1369: The Weeknd | G1369: 93 | H1369: 112918137 | I1369: r&b pop, alternative r&b, hip hop, synthpop | J1369: 18sR8zHx4zsVJUI4bHWuPC | K1369: The Highlights (Deluxe) | L1369: 45331 | M1369: 36 | N1369: compilation | O1369: 5.81
A1370: 3w0w2T288dec0mgeZZqoNN | B1370: CARNIVAL | C1370: 12 | D1370: 10 | E1370: TRUE | F1370: ¬•$ | G1370: 69 | H1370: 1042697 | I1370: N/A | J1370: 30zwjSQEodaUXCn11nmiVF | K1370: VULTURES 1 | L1370: 45331 | M1370: 16 | N1370: album | O1370: 4.4
A1371: 51TYqTZ1eTZsHVcrt0mmqe | B1371: Cruel Summer | C1371: 7 | D1371: 39 | E1371: FALSE | F1371: RIELL | G1371: 52 | H1371: 78478 | I1371: N/A | J1371: 4YEfCWcwGgaUa0YAY8CUJZ | K1371: love 4.0 | L1371: 45331 | M1371: 13 | N1371: compilation | O1371: 3.97
A1372: 6G5tgXgOJy58YWGCMpkiCa | B1372: Drowning In Us | C1372: 1 | D1372: 20 | E1372: FALSE | F1372: Now O Later | G1372: 43 | H1372: 2595 | I1372: hypertechno | J1372: 0UsKmlCH7ORHS15slJMv3p | K1372: Drowning In Us | L1372: 45331 | M1372: 1 | N1372: single | O1372: 2.56
A1373: 1hFmDg5nxATVqQL1Viaed2 | B1373: Lovin On Me | C1373: 1 | D1373: 40 | E1373: FALSE | F1373: midnight Berlin | G1373: 42 | H1373: 4083 | I1373: hypertechno | J1373: 7abSe0mEKF1gkIDckeHd2F | K1373: Lovin On Me | L1373: 45331 | M1373: 1 | N1373: single | O1373: 2.28
... A1462: 5mY6WIHXoBsOCSyQxrTg0E | B1462: VALENTINE | C1462: 2 | D1462: 64 | E1462: FALSE | F1462: M√•neskin | G1462: 76 | H1462: 10636129 | I1462: N/A | J1462: 2kcJ3TxBhSwmki0QWFXUz8 | K1462: RUSH! (ARE U COMING?) | L1462: 45240 | M1462: 22 | N1462: album | O1462: 3.61
A1463: 3XqM8hLCEYlbnFjoWwqtFv | B1463: Angel Numbers / Ten Toes | C1463: 1 | D1463: 77 | E1463: TRUE | F1463: Chris Brown | G1463: 87 | H1463: 28327351 | I1463: r&b | J1463: 0tL8CzbfmF5poGm9puqALR | K1463: 0.46597222 | L1463: 45240 | M1463: 22 | N1463: album | O1463: 5.11
A1464: 5hT3U17QZiP74YN9xF32JG | B1464: Better Off (Alone, Pt. III) | C1464: 4 | D1464: 3 | E1464: FALSE | F1464: Alan Walker | G1464: 78 | H1464: 41264069 | I1464: N/A | J1464: 3bKcoHSsmTEWHAGXqwOneo | K1464: Walkerworld | L1464: 45240 | M1464: 10 | N1464: album | O1464: 2.52
A1465: 17PVZrZPFBjFhNqx0YLF7o | B1465: BLA BLA BLA | C1465: 9 | D1465: 50 | E1465: TRUE | F1465: M√•neskin | G1465: 76 | H1465: 10638829 | I1465: N/A | J1465: 2kcJ3TxBhSwmki0QWFXUz8 | K1465: RUSH! (ARE U COMING?) | L1465: 45240 | M1465: 22 | N1465: album | O1465: 3.07
A1466: 6k01DY0P3ztcD75wSYWUsk | B1466: GASOLINE | C1466: 11 | D1466: 51 | E1466: FALSE | F1466: M√•neskin | G1466: 76 | H1466: 10637574 | I1466: N/A | J1466: 2kcJ3TxBhSwmki0QWFXUz8 | K1466: RUSH! (ARE U COMING?) | L1466: 45240 | M1466: 22 | N1466: album | O1466: 3.68
A1467: 4xhsWYTOGcal8zt0J161CU | B1467: Lovin On Me | C1467: 1 | D1467: 77 | E1467: TRUE | F1467: Jack Harlow | G1467: 75 | H1467: 4349241 | I1467: N/A | J1467: 6VCO0fDBGbRW8mCEvV95af | K1467: Lovin On Me | L1467: 45240 | M1467: 1 | N1467: single | O1467: 2.3
A1468: 3DrkYwyu8QqZQ05r2gGqHi | B1468: Mosquito | C1468: 3 | D1468: 63 | E1468: FALSE | F1468: PinkPantheress | G1468: 78 | H1468: 4761364 | I1468: bedroom pop | J1468: 2pOEFqvfxp5uUQ8vQEmVA0 | K1468: Heaven knows | L1468: 45240 | M1468: 13 | N1468: album | O1468: 2.43
A1469: 1XBYiRV30ykHw5f4wm6qEn | B1469: NIGHTS LIKE THIS | C1469: 8 | D1469: 86 | E1469: FALSE | F1469: The Kid LAROI | G1469: 79 | H1469: 6595164 | I1469: N/A | J1469: 63IolVUykZCHMlu2zu9jHS | K1469: THE FIRST TIME | L1469: 45240 | M1469: 20 | N1469: album | O1469: 1.44
A1470: 1FGwDURKxW4gK5DRiCvD9Y | B1470: nostalgia.mp3 | C1470: 1 | D1470: 42 | E1470: FALSE | F1470: jan2k1 | G1470: 28 | H1470: 2843 | I1470: breakcore, jungle | J1470: 5EQ3BtcZwPAI6JprpxYEO3 | K1470: nostalgia.mp3 | L1470: 45240 | M1470: 3 | N1470: single | O1470: 1.31
A1471: 0cyQuiFTVaHM70y8xRsOWA | B1471: OFF MY FACE | C1471: 3 | D1471: 65 | E1471: FALSE | F1471: M√•neskin | G1471: 76 | H1471: 10640396 | I1471: N/A | J1471: 2kcJ3TxBhSwmki0QWFXUz8 | K1471: RUSH! (ARE U COMING?) | L1471: 45240 | M1471: 22 | N1471: album | O1471: 2.49
A1472: 7Ey8DZuMBbeiqMk8s8XpHA | B1472: RUSH | C1472: 1 | D1472: 62 | E1472: FALSE | F1472: Dutch Melrose | G1472: 64 | H1472: 318012 | I1472: dark r&b | J1472: 4SAyGeqK3PpEVRNPp9ha89 | K1472: RUSH | L1472: 45240 | M1472: 2 | N1472: single | O1472: 2.86
...

Sheet genres
A1: artist_name | B1: artist_followers | C1: artist_genres
A2: Diplo | B2: 2812821 | C2: moombahton | N2: Row Labels | O2: Count of artist_name
A3: Yelawolf | B3: 2363438 | C3: country hip hop | D3: southern hip hop | N3: alternative pop | O3: 160
A4: Riff Raff | B4: 193302 | C4: N/A | N4: art pop | O4: 115
A5: Diplo | B5: 2813710 | C5: moombahton | N5: country | O5: 572
A6: Rumelis | B6: 8682 | C6: dark r&b | N6: dark r&b | O6: 118
A7: Minzie | B7: 7218 | C7: dark r&b | N7: pop | O7: 516
A8: AZERDK | B8: 1657 | C8: N/A | N8: pop rock | O8: 100
A9: Rumelis | B9: 8802 | C9: dark r&b | N9: r&b pop | O9: 141
A10: Toni dos Anjos | B10: 475 | C10: N/A | N10: rap | O10: 268
A11: PsychoYP | B11: 154802 | C11: nigerian drill | D11: alt√© | E11: afro adura | F11: afrobeats | G11: afrobeat | H11: afroswing | N11: soft pop | O11: 213
A12: What Matters The Most | B12: 814 | C12: N/A | N12: soundtrack | O12: 352
A13: A2O | B13: 13826 | C13: c-pop | N13: Grand Total | O13: 2555
A14: Daniel Caesar | B14: 11137714 | C14: N/A
A15: Ovi Jozi | B15: 3567 | C15: N/A
A16: A2O | B16: 13590 | C16: c-pop
A17: Leon Thomas | B17: 735818 | C17: N/A
A18: Joe Hermes | B18: 1518 | C18: N/A
A19: A2O | B19: 13826 | C19: c-pop
A20: Scarlett Butler | B20: 364 | C20: N/A
A21: LEROCQUE | B21: 13770 | C21: N/A
A22: Xander Ward | B22: 729 | C22: N/A
A23: The All-American Rejects | B23: 3134186 | C23: pop punk | D23: emo
A24: Smith & Liddle | B24: 543 | C24: N/A
A25: Artemas | B25: 1378935 | C25: N/A
A26: YUNG ALPO | B26: 166 | C26: N/A
A27: A2O | B27: 13826 | C27: c-pop
A28: PRAX | B28: 1982 | C28: N/A
A29: Mark II | B29: 722 | C29: N/A
A30: Suark | B30: 1496 | C30: N/A
A31: Vince Bello | B31: 84 | C31: N/A
A32: Anna Marx | B32: 1693 | C32: N/A
A33: Ana Shine | B33: 27570 | C33: N/A
A34: Stray Currents | B34: 1073 | C34: N/A
A35: Sopperior | B35: 2891 | C35: N/A
... A40: Besomorph | B40: 146944 | C40: slap house
A41: Tame Impala | B41: 9509731 | C41: neo-psychedelic | D41: indie
A42: Diplo | B42: 2812337 | C42: moombahton
A43: Ken | B43: 7219 | C43: hypertechno
A44: Kxng Le√≥ | B44: 177 | C44: N/A
A45: Kayote | B45: 19306 | C45: N/A
A46: Sam Fender | B46: 1204977 | C46: N/A
A47: Lila Holler | B47: 1068 | C47: N/A
A48: Sonny Fodera | B48: 306842 | C48: house
A49: Annalise Azadian | B49: 5701 | C49: N/A
A50: Ex Habit | B50: 130408 | C50: dark r&b
A51: Poul | B51: 1161 | C51: N/A
A52: Abeer Nehme | B52: 247771 | C52: sholawat | D52: khaleeji
A53: Joji | B53: 10638942 | C53: N/A
A54: Stanza | B54: 218 | C54: N/A
A55: Christian Kennedy | B55: 297 | C55: N/A
A56: Rod Wave | B56: 9673984 | C56: N/A
A57: David Guetta | B57: 27141717 | C57: edm
A58: Olivia Cox | B58: 1263 | C58: hipdut
A59: Briezman | B59: 445 | C59: big room
A60: TAMMO | B60: 290 | C60: N/A
A61: A Boogie Wit da Hoodie | B61: 8986062 | C61: melodic rap
A62: Jason Charles Miller | B62: 17999 | C62: N/A
A63: Visibly True | B63: 114 | C63: N/A
A64: The Haygoods | B64: 7785 | C64: N/A
... A71: Millo | B71: 429 | C71: N/A
A72: KOLBEIN | B72: 631 | C72: hypertechno | D72: melbourne bounce
A73: ASH7ON | B73: 308 | C73: N/A
A74: KROMA | B74: 11283 | C74: hard techno
A75: zukrassverliebt | B75: 435 | C75: N/A
A76: Riff Raff | B76: 193279 | C76: N/A
A77: TIMBER | B77: 37 | C77: N/A
A78: Maithili Raelle | B78: 2633 | C78: N/A
A79: Sabir | B79: 435 | C79: N/A
A80: Taylor Swift | B80: 145443567 | C80: country | D80: pop | E80: indie | F80: folk
A81: Taylor Swift | B81: 145489371 | C81: country | D81: pop | E81: indie | F81: folk
A82: Besomorph | B82: 146969 | C82: slap house
A83: Padre T√≥xico | B83: 13179 | C83: jazz rap
A84: Orvyn Sol | B84: 48 | C84: N/A
A85: MEDZ | B85: 6199 | C85: melodic bass | D85: future bass
A86: Edd Stark | B86: 405 | C86: chicago drill
A87: IV Tune | B87: 54 | C87: N/A
A88: Taylor Swift | B88: 145396321 | C88: country | D88: pop | E88: indie | F88: folk
A89: IAN SIZE | B89: 1844 | C89: melodic bass | D89: nightcore | E89: bass music
A90: Taylor Swift | B90: 145443567 | C90: country | D90: pop | E90: indie | F90: folk
A91: Beatline | B91: 475 | C91: future house
A92: Taylor Swift | B92: 145489371 | C92: country | D92: pop | E92: indie | F92: folk
A93: Rumelis | B93: 8741 | C93: dark r&b
A94: Third Vibes | B94: 3776 | C94: N/A
A95: Taylor Swift | B95: 145396321 | C95: country | D95: pop | E95: indie | F95: folk
A96: Phay | B96: 5344 | C96: N/A
A97: Taylor Swift | B97: 145396321 | C97: country | D97: pop | E97: indie | F97: folk
A98: Taylor Swift | B98: 145396321 | C98: country | D98: pop | E98: indie | F98: folk
A99: Taylor Swift | B99: 145443567 | C99: country | D99: pop | E99: indie | F99: folk
A100: Fred again.. | B100: 2201446 | C100: stutter house | D100: house
A101: Luke Combs | B101: 13402920 | C101: country
A102: Taylor Swift | B102: 145396321 | C102: country | D102: pop | E102: indie | F102: folk
A103: Taylor Swift | B103: 145489371 | C103: country | D103: pop | E103: indie | F103: folk
A104: Tolou | B104: 4401 | C104: N/A
A105: Taylor Swift | B105: 145542136 | C105: country | D105: pop | E105: indie | F105: folk
A106: Haifa Wehbe | B106: 1151605 | C106: egyptian pop | D106: khaleeji
A107: Taylor Swift | B107: 145443567 | C107: country | D107: pop | E107: indie | F107: folk
A108: Lindsey Fish | B108: 3629 | C108: N/A
A109: Van Herpen | B109: 1081 | C109: N/A
A110: Eiza Murphy | B110: 4162 | C110: N/A
...

Sheet Charts
AI6: Row Labels | AJ6: Average of artist_followers
AI7: Taylor Swift | AJ7: 1.4543996e+08
AI8: Ed Sheeran | AJ8: 1.2278474e+08
AI9: Billie Eilish | AJ9: 1.1871188e+08
AI10: The Weeknd | AJ10: 1.1295567e+08
AI11: Ariana Grande | AJ11: 1.073897e+08
AI12: Eminem | AJ12: 1.0453655e+08
AI13: Drake | AJ13: 1.0306154e+08
AI14: Bad Bunny | AJ14: 1.0253335e+08
AI15: Justin Bieber | AJ15: 85020552
AI16: BTS | AJ16: 81187032
AI17: Grand Total | AJ17: 1.1959344e+08
J18: Years (album_release_date) | K18: (Multiple Items)
K20: Column Labels
K21: Taylor Swift | L21: The Weeknd | M21: Post Malone | N21: Ariana Grande | O21: Drake | P21: Olivia Rodrigo | Q21: Billie Eilish | R21: Lil Peep | S21: Bad Bunny | T21: Tate McRae
J22: Count of track_id | K22: 250 | L22: 106 | M22: 83 | N22: 82 | O22: 73 | P22: 68 | Q22: 61 | R22: 60 | S22: 56 | T22: 48
AF35: Row Labels | AG35: Count of track_id
AF36: 2015 | AG36: 383
AF37: 2016 | AG37: 376
AF38: 2017 | AG38: 458
AF39: 2018 | AG39: 522
AF40: 2019 | AG40: 496
AF41: 2020 | AG41: 480
AF42: 2021 | AG42: 443
AF43: 2022 | AG43: 468
AF44: 2023 | AG44: 523
AF45: 2024 | AG45: 648
AF46: 2025 | AG46: 765
AF47: Grand Total | AG47: 5562
J48: Row Labels | K48: Average of artist_popularity | L48: Count of track_id | P48: correl | R48: Row Labels | S48: Count of track_id | T48: Average of artist_followers | X48: correl
J49: $uicideboy$ | K49: 83 | L49: 2 | M49: 83 | N49: 2 | P49: =CORREL(M49:M155,N49:N155) -> 0.65883552 | R49: Taylor Swift | S49: 324 | T49: 1.4543996e+08 | X49: =CORREL(U50:U155,V50:V155) -> 0.63426329
J50: 21 Savage | K50: 84 | L50: 7 | M50: 84 | N50: 7 | R50: Ed Sheeran | S50: 53 | T50: 1.2278474e+08 | U50: 53 | V50: 1.2278474e+08
J51: 50 Cent | K51: 82 | L51: 6 | M51: 82 | N51: 6 | R51: Billie Eilish | S51: 61 | T51: 1.1871188e+08 | U51: 61 | V51: 1.1871188e+08
J52: A$AP Rocky | K52: 82 | L52: 7 | M52: 82 | N52: 7 | R52: The Weeknd | S52: 141 | T52: 1.1295567e+08 | U52: 141 | V52: 1.1295567e+08
J53: Adele | K53: 83 | L53: 41 | M53: 83 | N53: 41 | R53: Ariana Grande | S53: 94 | T53: 1.073897e+08 | U53: 94 | V53: 1.073897e+08
J54: Alex Warren | K54: 84 | L54: 5 | M54: 84 | N54: 5 | R54: Eminem | S54: 67 | T54: 1.0453655e+08 | U54: 67 | V54: 1.0453655e+08
J55: Arc√°ngel | K55: 82 | L55: 1 | M55: 82 | N55: 1 | R55: Drake | S55: 84 | T55: 1.0306154e+08 | U55: 84 | V55: 1.0306154e+08
J56: Arctic Monkeys | K56: 84 | L56: 10 | M56: 84 | N56: 10 | R56: Bad Bunny | S56: 56 | T56: 1.0253335e+08 | U56: 56 | V56: 1.0253335e+08
J57: Ariana Grande | K57: 90 | L57: 94 | M57: 90 | N57: 94 | R57: Justin Bieber | S57: 55 | T57: 85020552 | U57: 55 | V57: 85020552
J58: Bad Bunny | K58: 95 | L58: 56 | M58: 95 | N58: 56 | R58: BTS | S58: 30 | T58: 81187032 | U58: 30 | V58: 81187032
J59: Benson Boone | K59: 83 | L59: 7 | M59: 83 | N59: 7 | R59: Bruno Mars | S59: 27 | T59: 75473429 | U59: 27 | V59: 75473429
J60: Beyonc√© | K60: 84 | L60: 49 | M60: 84 | N60: 49 | R60: Rihanna | S60: 52 | T60: 69009261 | U60: 52 | V60: 69009261
J61: Billie Eilish | K61: 90 | L61: 61 | M61: 90 | N61: 61 | R61: Adele | S61: 41 | T61: 66721537 | U61: 41 | V61: 66721537
... J155: Zach Bryan | K155: 84 | L155: 2 | M155: 84 | N155: 2 | R155: Led Zeppelin | S155: 1 | T155: 15974926 | U155: 1 | V155: 15974926
J156: Grand Total | K156: 88.512115 | L156: 2724 | R156: Justin Timberlake | S156: 10 | T156: 15825084
R157: Bon Jovi | S157: 6 | T157: 15807539
R158: Meghan Trainor | S158: 5 | T158: 15743917
R159: The Rolling Stones | S159: 3 | T159: 15712085
R160: Manuel Turizo | S160: 1 | T160: 15711025
R161: Snoop Dogg | S161: 4 | T161: 15695065
R162: Lil Peep | S162: 60 | T162: 15689931
R163: Pop Smoke | S163: 5 | T163: 15614266
R164: Elton John | S164: 5 | T164: 15543010
R165: Martin Garrix | S165: 6 | T165: 15121543
R166: Dr. Dre | S166: 6 | T166: 15088992
R167: Playboi Carti | S167: 45 | T167: 15028336
R168: YoungBoy Never Broke Again | S168: 5 | T168: 14943530
... R2597: Grand Total | S2597: 8582 | T2597: 24034719

Sheet Dashboard
